[
  {
    "id": 1,
    "title": "Mary Mahoney's Old French House",
    "slug": "mary-mahoneys-old-french-house",
    "status": "publish",
    "content": "Legendary fine dining restaurant housed in one of America's oldest buildings, dating to 1737. Specializes in locally sourced Gulf seafood and prime steaks with a romantic courtyard setting. Family owned and operated for over 60 years.",
    "excerpt": "",
    "post_date": "2026-03-10T12:00:00",
    "address": "110 Rue Magnolia, Biloxi, MS 39530",
    "phone": "(228) 374-0163",
    "email": "",
    "website": "https://www.marymahoneys.com/",
    "latitude": "",
    "longitude": "",
    "featured": false,
    "categories": ["Restaurants & Dining"],
    "location": ["Biloxi"],
    "tags": [],
    "deal_title": "",
    "deal_description": "",
    "deal_expiry": ""
  },
  {
    "id": 2,
    "title": "Shaggy's Biloxi Beach",
    "slug": "shaggys-biloxi-beach",
    "status": "publish",
    "content": "Casual beachfront restaurant serving fried shrimp, po'boys, and fresh Gulf seafood with spectacular sunset views. Family-friendly atmosphere right on the water.",
    "excerpt": "",
    "post_date": "2026-03-10T12:00:00",
    "address": "1763 Beach Blvd, Biloxi, MS 39531",
    "phone": "(228) 432-4455",
    "email": "",
    "website": "https://www.shaggys.com/",
    "latitude": "",
    "longitude": "",
    "featured": false,
    "categories": ["Restaurants & Dining"],
    "location": ["Biloxi"],
    "tags": [],
    "deal_title": "",
    "deal_description": "",
    "deal_expiry": ""
  },
  {
    "id": 3,
    "title": "Half Shell Oyster House",
    "slug": "half-shell-oyster-house-biloxi",
    "status": "publish",
    "content": "Award-winning seafood restaurant known for chargrilled oysters, fresh Gulf catches, and Southern hospitality. A Gulf Coast favorite with a vibrant atmosphere.",
    "excerpt": "",
    "post_date": "2026-03-10T12:00:00",
    "address": "2500 Beach Blvd Suite E, Biloxi, MS 39531",
    "phone": "(228) 432-4656",
    "email": "",
    "website": "https://www.halfshelloysterhouse.com/",
    "latitude": "",
    "longitude": "",
    "featured": false,
    "categories": ["Restaurants & Dining"],
    "location": ["Biloxi"],
    "tags": [],
    "deal_title": "",
    "deal_description": "",
    "deal_expiry": ""
  },
  {
    "id": 4,
    "title": "Patio 44",
    "slug": "patio-44-biloxi",
    "status": "publish",
    "content": "Upscale casual restaurant featuring a chef-driven menu with fine ingredients, a wine list of over 100 bottles, and hand-crafted cocktails. Beautiful 50-seat patio and elegant indoor dining.",
    "excerpt": "",
    "post_date": "2026-03-10T12:00:00",
    "address": "2218 25th Ave, Gulfport, MS 39501",
    "phone": "(228) 220-4414",
    "email": "",
    "website": "https://www.patio44gulfcoast.com/",
    "latitude": "",
    "longitude": "",
    "featured": false,
    "categories": ["Restaurants & Dining"],
    "location": ["Gulfport"],
    "tags": [],
    "deal_title": "",
    "deal_description": "",
    "deal_expiry": ""
  },
  {
    "id": 5,
    "title": "The Greenhouse on Porter",
    "slug": "the-greenhouse-on-porter",
    "status": "publish",
    "content": "Cozy neighborhood cafe famous for its scratch-made biscuits with creative toppings. Sweet potato and bacon cheddar biscuits are local favorites. Serves breakfast and lunch.",
    "excerpt": "",
    "post_date": "2026-03-10T12:00:00",
    "address": "1230 Porter Ave, Biloxi, MS 39530",
    "phone": "(228) 354-5848",
    "email": "",
    "website": "https://www.thegreenhouseonporter.com/",
    "latitude": "",
    "longitude": "",
    "featured": false,
    "categories": ["Restaurants & Dining"],
    "location": ["Biloxi"],
    "tags": [],
    "deal_title": "",
    "deal_description": "",
    "deal_expiry": ""
  },
  {
    "id": 6,
    "title": "Vestige",
    "slug": "vestige-biloxi",
    "status": "publish",
    "content": "Acclaimed fine dining restaurant recognized by the MICHELIN Guide. Features a seasonal menu with locally sourced ingredients and innovative Gulf Coast cuisine.",
    "excerpt": "",
    "post_date": "2026-03-10T12:00:00",
    "address": "1200 Government St, Ocean Springs, MS 39564",
    "phone": "(228) 818-0950",
    "email": "",
    "website": "https://www.vestigerestaurant.com/",
    "latitude": "",
    "longitude": "",
    "featured": false,
    "categories": ["Restaurants & Dining"],
    "location": ["Biloxi"],
    "tags": [],
    "deal_title": "",
    "deal_description": "",
    "deal_expiry": ""
  },
  {
    "id": 7,
    "title": "McElroy's Harbor House",
    "slug": "mcelroys-harbor-house",
    "status": "publish",
    "content": "Waterfront seafood restaurant overlooking the Biloxi Small Craft Harbor. Known for fresh Gulf seafood, cold drinks, and stunning harbor views.",
    "excerpt": "",
    "post_date": "2026-03-10T12:00:00",
    "address": "695 Beach Blvd, Biloxi, MS 39530",
    "phone": "(228) 435-5001",
    "email": "",
    "website": "https://www.mcelroysharborhouse.com/",
    "latitude": "",
    "longitude": "",
    "featured": false,
    "categories": ["Restaurants & Dining"],
    "location": ["Biloxi"],
    "tags": [],
    "deal_title": "",
    "deal_description": "",
    "deal_expiry": ""
  },
  {
    "id": 8,
    "title": "Catch 110",
    "slug": "catch-110",
    "status": "publish",
    "content": "Modern coastal dining with an impressive wine list, hand-crafted cocktails, and locally sourced Gulf Coast seafood. Features two patios with a picture-perfect setting.",
    "excerpt": "",
    "post_date": "2026-03-10T12:00:00",
    "address": "110 Lameuse St, Biloxi, MS 39530",
    "phone": "(228) 374-3110",
    "email": "",
    "website": "",
    "latitude": "",
    "longitude": "",
    "featured": false,
    "categories": ["Restaurants & Dining"],
    "location": ["Biloxi"],
    "tags": [],
    "deal_title": "",
    "deal_description": "",
    "deal_expiry": ""
  },
  {
    "id": 9,
    "title": "The Blow Fly Inn",
    "slug": "the-blow-fly-inn",
    "status": "publish",
    "content": "Iconic Gulfport seafood institution serving classic Gulf Coast fare since 1953. Famous for its no-frills atmosphere, boiled shrimp, po'boys, and cold beer.",
    "excerpt": "",
    "post_date": "2026-03-10T12:00:00",
    "address": "1201 Washington Ave, Gulfport, MS 39507",
    "phone": "(228) 896-9812",
    "email": "",
    "website": "",
    "latitude": "",
    "longitude": "",
    "featured": false,
    "categories": ["Restaurants & Dining"],
    "location": ["Gulfport"],
    "tags": [],
    "deal_title": "",
    "deal_description": "",
    "deal_expiry": ""
  },
  {
    "id": 10,
    "title": "Murky Waters Blues & BBQ",
    "slug": "murky-waters-blues-bbq",
    "status": "publish",
    "content": "Barbecue joint combining smoked meats with live blues music. Serves pulled pork, ribs, brisket, and classic Southern sides in a lively atmosphere.",
    "excerpt": "",
    "post_date": "2026-03-10T12:00:00",
    "address": "3009 13th St, Gulfport, MS 39501",
    "phone": "(228) 868-7867",
    "email": "",
    "website": "",
    "latitude": "",
    "longitude": "",
    "featured": false,
    "categories": ["Restaurants & Dining"],
    "location": ["Gulfport"],
    "tags": [],
    "deal_title": "",
    "deal_description": "",
    "deal_expiry": ""
  },
  {
    "id": 11,
    "title": "Shaggy's Gulfport Beach",
    "slug": "shaggys-gulfport-beach",
    "status": "publish",
    "content": "Beachfront seafood and bar serving fresh Gulf catches, burgers, and tropical drinks with a laid-back coastal atmosphere and sunset views.",
    "excerpt": "",
    "post_date": "2026-03-10T12:00:00",
    "address": "1758 E Beach Blvd, Gulfport, MS 39501",
    "phone": "(228) 257-4793",
    "email": "",
    "website": "https://www.shaggys.com/",
    "latitude": "",
    "longitude": "",
    "featured": false,
    "categories": ["Restaurants & Dining"],
    "location": ["Gulfport"],
    "tags": [],
    "deal_title": "",
    "deal_description": "",
    "deal_expiry": ""
  },
  {
    "id": 12,
    "title": "Flatheads and Bottom Feeders",
    "slug": "flatheads-and-bottom-feeders",
    "status": "publish",
    "content": "Popular seafood restaurant offering fresh Gulf catches, catfish, and creative Southern dishes. Consistently rated among the best restaurants in Gulfport.",
    "excerpt": "",
    "post_date": "2026-03-10T12:00:00",
    "address": "3101 13th St, Gulfport, MS 39501",
    "phone": "(228) 452-0145",
    "email": "",
    "website": "",
    "latitude": "",
    "longitude": "",
    "featured": false,
    "categories": ["Restaurants & Dining"],
    "location": ["Gulfport"],
    "tags": [],
    "deal_title": "",
    "deal_description": "",
    "deal_expiry": ""
  },
  {
    "id": 13,
    "title": "White Pillars Restaurant",
    "slug": "white-pillars-restaurant",
    "status": "publish",
    "content": "Farm-to-table fine dining in a restored 1905 beachfront home. Led by James Beard semifinalist Chef Austin Sumrall, featuring seasonal Gulf Coast cuisine with locally sourced ingredients.",
    "excerpt": "",
    "post_date": "2026-03-10T12:00:00",
    "address": "216 E Beach Blvd, Long Beach, MS 39560",
    "phone": "(228) 863-1322",
    "email": "",
    "website": "https://www.whitepillarsrestaurant.com/",
    "latitude": "",
    "longitude": "",
    "featured": false,
    "categories": ["Restaurants & Dining"],
    "location": ["Long Beach"],
    "tags": [],
    "deal_title": "",
    "deal_description": "",
    "deal_expiry": ""
  },
  {
    "id": 14,
    "title": "Lil' Ray's Seafood & Po'boys",
    "slug": "lil-rays-seafood-and-poboys",
    "status": "publish",
    "content": "Gulf Coast seafood institution since 1970 serving spicy boiled shrimp, crawfish, fried oysters, gumbo, and po'boys in every variety. A local favorite.",
    "excerpt": "",
    "post_date": "2026-03-10T12:00:00",
    "address": "113 E 2nd St, Long Beach, MS 39560",
    "phone": "(228) 864-9988",
    "email": "",
    "website": "https://www.lilrayslongbeach.com/",
    "latitude": "",
    "longitude": "",
    "featured": false,
    "categories": ["Restaurants & Dining"],
    "location": ["Long Beach"],
    "tags": [],
    "deal_title": "",
    "deal_description": "",
    "deal_expiry": ""
  },
  {
    "id": 15,
    "title": "Radish",
    "slug": "radish-long-beach",
    "status": "publish",
    "content": "Chef-driven restaurant in downtown Long Beach embracing time-honored techniques to create an ingredient-driven menu showcasing Southern cuisine and cocktails.",
    "excerpt": "",
    "post_date": "2026-03-10T12:00:00",
    "address": "120 Jeff Davis Ave, Long Beach, MS 39560",
    "phone": "(228) 867-7575",
    "email": "",
    "website": "https://www.radishlongbeach.com/",
    "latitude": "",
    "longitude": "",
    "featured": false,
    "categories": ["Restaurants & Dining"],
    "location": ["Long Beach"],
    "tags": [],
    "deal_title": "",
    "deal_description": "",
    "deal_expiry": ""
  },
  {
    "id": 16,
    "title": "Long Beach Market & Deli",
    "slug": "long-beach-market-and-deli",
    "status": "publish",
    "content": "Family-owned establishment featuring the largest cold beer selection in Mississippi. Menu spans Korean, Chinese, Cajun, Vietnamese, and American dishes crafted by Le Cordon Bleu-trained chef.",
    "excerpt": "",
    "post_date": "2026-03-10T12:00:00",
    "address": "100 Jeff Davis Ave, Long Beach, MS 39560",
    "phone": "(228) 864-4747",
    "email": "",
    "website": "http://www.lbmarketanddeli.com/",
    "latitude": "",
    "longitude": "",
    "featured": false,
    "categories": ["Restaurants & Dining"],
    "location": ["Long Beach"],
    "tags": [],
    "deal_title": "",
    "deal_description": "",
    "deal_expiry": ""
  },
  {
    "id": 17,
    "title": "Darwell's Cafe",
    "slug": "darwells-cafe",
    "status": "publish",
    "content": "Eclectic and colorful cafe in downtown Long Beach known for creative sandwiches, salads, and a fun, quirky atmosphere. A beloved Gulf Coast dining destination.",
    "excerpt": "",
    "post_date": "2026-03-10T12:00:00",
    "address": "127 Jeff Davis Ave, Long Beach, MS 39560",
    "phone": "(228) 867-2774",
    "email": "",
    "website": "",
    "latitude": "",
    "longitude": "",
    "featured": false,
    "categories": ["Restaurants & Dining"],
    "location": ["Long Beach"],
    "tags": [],
    "deal_title": "",
    "deal_description": "",
    "deal_expiry": ""
  },
  {
    "id": 18,
    "title": "Cafe New Orleans",
    "slug": "cafe-new-orleans-diberville",
    "status": "publish",
    "content": "Family-owned Cajun restaurant since 2000 serving authentic Louisiana-style dishes including gumbo, crawfish, and Southern comfort food in a welcoming atmosphere.",
    "excerpt": "",
    "post_date": "2026-03-10T12:00:00",
    "address": "11014 Lamey Bridge Rd, D'Iberville, MS 39540",
    "phone": "(228) 396-6269",
    "email": "",
    "website": "https://cafeneworleans.net/",
    "latitude": "",
    "longitude": "",
    "featured": false,
    "categories": ["Restaurants & Dining"],
    "location": ["D'Iberville"],
    "tags": [],
    "deal_title": "",
    "deal_description": "",
    "deal_expiry": ""
  },
  {
    "id": 19,
    "title": "Twin Peaks",
    "slug": "twin-peaks-diberville",
    "status": "publish",
    "content": "Sports bar and restaurant featuring scratch-made food, ice-cold draft beer served at 29 degrees, and big-screen TVs. Located at the heart of D'Iberville.",
    "excerpt": "",
    "post_date": "2026-03-10T12:00:00",
    "address": "10598 Lamey Bridge Rd, D'Iberville, MS 39540",
    "phone": "(228) 207-2800",
    "email": "",
    "website": "https://twinpeaksrestaurant.com/locations/diberville-ms",
    "latitude": "",
    "longitude": "",
    "featured": false,
    "categories": ["Restaurants & Dining"],
    "location": ["D'Iberville"],
    "tags": [],
    "deal_title": "",
    "deal_description": "",
    "deal_expiry": ""
  },
  {
    "id": 20,
    "title": "Chopstx Noodle Bar",
    "slug": "chopstx-noodle-bar",
    "status": "publish",
    "content": "Vietnamese-inspired restaurant serving pho noodle soups, banh mi sandwiches, appetizers, and Asian fusion dishes in D'Iberville.",
    "excerpt": "",
    "post_date": "2026-03-10T12:00:00",
    "address": "10491 D'Iberville Blvd, D'Iberville, MS 39540",
    "phone": "(228) 354-5399",
    "email": "",
    "website": "",
    "latitude": "",
    "longitude": "",
    "featured": false,
    "categories": ["Restaurants & Dining"],
    "location": ["D'Iberville"],
    "tags": [],
    "deal_title": "",
    "deal_description": "",
    "deal_expiry": ""
  },
  {
    "id": 21,
    "title": "Tigre's Restaurant & Lounge",
    "slug": "tigres-restaurant-and-lounge",
    "status": "publish",
    "content": "Popular Pass Christian eatery serving Southern cuisine, seafood, and steaks in a welcoming downtown atmosphere on Second Street.",
    "excerpt": "",
    "post_date": "2026-03-10T12:00:00",
    "address": "101 W 2nd St, Pass Christian, MS 39571",
    "phone": "(228) 452-9800",
    "email": "",
    "website": "",
    "latitude": "",
    "longitude": "",
    "featured": false,
    "categories": ["Restaurants & Dining"],
    "location": ["Pass Christian"],
    "tags": [],
    "deal_title": "",
    "deal_description": "",
    "deal_expiry": ""
  },
  {
    "id": 22,
    "title": "Hook Gulf Coast Cuisine",
    "slug": "hook-gulf-coast-cuisine",
    "status": "publish",
    "content": "Locally owned restaurant in downtown Pass Christian featuring fresh Gulf seafood, creative coastal dishes, and a warm neighborhood atmosphere.",
    "excerpt": "",
    "post_date": "2026-03-10T12:00:00",
    "address": "119 W Davis Ave, Pass Christian, MS 39571",
    "phone": "(228) 222-4665",
    "email": "",
    "website": "",
    "latitude": "",
    "longitude": "",
    "featured": false,
    "categories": ["Restaurants & Dining"],
    "location": ["Pass Christian"],
    "tags": [],
    "deal_title": "",
    "deal_description": "",
    "deal_expiry": ""
  },
  {
    "id": 23,
    "title": "Rusty Pelican",
    "slug": "rusty-pelican-pass-christian",
    "status": "publish",
    "content": "Casual beachfront restaurant on East Beach Boulevard serving po'boys, burgers, fresh seafood plates, and cold drinks with Gulf views.",
    "excerpt": "",
    "post_date": "2026-03-10T12:00:00",
    "address": "1525 E Beach Blvd, Pass Christian, MS 39571",
    "phone": "(228) 452-5800",
    "email": "",
    "website": "",
    "latitude": "",
    "longitude": "",
    "featured": false,
    "categories": ["Restaurants & Dining"],
    "location": ["Pass Christian"],
    "tags": [],
    "deal_title": "",
    "deal_description": "",
    "deal_expiry": ""
  },
  {
    "id": 24,
    "title": "Dixie Diner",
    "slug": "dixie-diner-saucier",
    "status": "publish",
    "content": "Family-friendly diner serving classic Southern comfort food including sandwiches, plate lunches, and homestyle cooking in Saucier.",
    "excerpt": "",
    "post_date": "2026-03-10T12:00:00",
    "address": "23430 Saucier Lizana Rd, Saucier, MS 39574",
    "phone": "(228) 284-5472",
    "email": "",
    "website": "",
    "latitude": "",
    "longitude": "",
    "featured": false,
    "categories": ["Restaurants & Dining"],
    "location": ["Saucier"],
    "tags": [],
    "deal_title": "",
    "deal_description": "",
    "deal_expiry": ""
  },
  {
    "id": 25,
    "title": "R & B Brick Oven Pizza",
    "slug": "r-and-b-brick-oven-pizza",
    "status": "publish",
    "content": "Brick oven pizzeria in Saucier serving hand-tossed pizzas, calzones, and Italian-American favorites baked in a traditional brick oven.",
    "excerpt": "",
    "post_date": "2026-03-10T12:00:00",
    "address": "23272 Hwy 49, Saucier, MS 39574",
    "phone": "(228) 832-2727",
    "email": "",
    "website": "",
    "latitude": "",
    "longitude": "",
    "featured": false,
    "categories": ["Restaurants & Dining"],
    "location": ["Saucier"],
    "tags": [],
    "deal_title": "",
    "deal_description": "",
    "deal_expiry": ""
  },
  {
    "id": 26,
    "title": "Parrain's Jambalaya Kitchen",
    "slug": "parrains-jambalaya-kitchen",
    "status": "publish",
    "content": "Cajun restaurant specializing in authentic Louisiana jambalaya, gumbo, crawfish, and Southern comfort dishes. A Biloxi favorite.",
    "excerpt": "",
    "post_date": "2026-03-10T12:00:00",
    "address": "2765 Beach Blvd, Biloxi, MS 39531",
    "phone": "(228) 354-5155",
    "email": "",
    "website": "",
    "latitude": "",
    "longitude": "",
    "featured": false,
    "categories": ["Restaurants & Dining"],
    "location": ["Biloxi"],
    "tags": [],
    "deal_title": "",
    "deal_description": "",
    "deal_expiry": ""
  },
  {
    "id": 27,
    "title": "Ground Zero Blues Club",
    "slug": "ground-zero-blues-club-biloxi",
    "status": "publish",
    "content": "Live music venue and bar co-owned by Morgan Freeman, serving Southern food and cold drinks with nightly blues, rock, and soul performances.",
    "excerpt": "",
    "post_date": "2026-03-10T12:00:00",
    "address": "871 Howard Ave, Biloxi, MS 39530",
    "phone": "(228) 374-4460",
    "email": "",
    "website": "https://groundzerobiloxi.com/",
    "latitude": "",
    "longitude": "",
    "featured": false,
    "categories": ["Bars & Nightlife"],
    "location": ["Biloxi"],
    "tags": [],
    "deal_title": "",
    "deal_description": "",
    "deal_expiry": ""
  },
  {
    "id": 28,
    "title": "Chandeleur Island Brewing Company",
    "slug": "chandeleur-island-brewing-company",
    "status": "publish",
    "content": "Craft brewery and taproom in Gulfport producing small-batch Gulf Coast-inspired beers. Features a rotating selection of ales, lagers, and seasonal brews.",
    "excerpt": "",
    "post_date": "2026-03-10T12:00:00",
    "address": "3101 13th St Suite D, Gulfport, MS 39501",
    "phone": "(228) 257-4520",
    "email": "",
    "website": "https://www.chandeleurislandbrewing.com/",
    "latitude": "",
    "longitude": "",
    "featured": false,
    "categories": ["Bars & Nightlife"],
    "location": ["Gulfport"],
    "tags": [],
    "deal_title": "",
    "deal_description": "",
    "deal_expiry": ""
  },
  {
    "id": 29,
    "title": "Bacchus on the Beach",
    "slug": "bacchus-on-the-beach",
    "status": "publish",
    "content": "Beachfront bar and restaurant in Long Beach serving craft cocktails, wine, cold beer, and light bites with beautiful Gulf sunset views.",
    "excerpt": "",
    "post_date": "2026-03-10T12:00:00",
    "address": "200 Jeff Davis Ave, Long Beach, MS 39560",
    "phone": "(228) 864-0611",
    "email": "",
    "website": "",
    "latitude": "",
    "longitude": "",
    "featured": false,
    "categories": ["Bars & Nightlife"],
    "location": ["Long Beach"],
    "tags": [],
    "deal_title": "",
    "deal_description": "",
    "deal_expiry": ""
  },
  {
    "id": 30,
    "title": "Oak & Vine",
    "slug": "oak-and-vine-biloxi",
    "status": "publish",
    "content": "Locally owned whiskey and wine bar featuring wine flights, mimosa towers, craft whiskeys, and curated charcuterie boards. A refined downtown Biloxi experience.",
    "excerpt": "",
    "post_date": "2026-03-10T12:00:00",
    "address": "880 Howard Ave, Biloxi, MS 39530",
    "phone": "(228) 207-2970",
    "email": "",
    "website": "",
    "latitude": "",
    "longitude": "",
    "featured": false,
    "categories": ["Bars & Nightlife"],
    "location": ["Biloxi"],
    "tags": [],
    "deal_title": "",
    "deal_description": "",
    "deal_expiry": ""
  },
  {
    "id": 31,
    "title": "Beau Rivage Resort & Casino",
    "slug": "beau-rivage-resort-and-casino",
    "status": "publish",
    "content": "Premier 32-story luxury casino resort with 1,740 rooms, world-class gaming, multiple restaurants including BR Prime and Stalla, a spa, pool, and top-name entertainment.",
    "excerpt": "",
    "post_date": "2026-03-10T12:00:00",
    "address": "875 Beach Blvd, Biloxi, MS 39530",
    "phone": "(228) 386-7111",
    "email": "",
    "website": "https://www.beaurivage.com/",
    "latitude": "",
    "longitude": "",
    "featured": false,
    "categories": ["Accommodations"],
    "location": ["Biloxi"],
    "tags": [],
    "deal_title": "",
    "deal_description": "",
    "deal_expiry": ""
  },
  {
    "id": 32,
    "title": "Hard Rock Hotel & Casino Biloxi",
    "slug": "hard-rock-hotel-and-casino-biloxi",
    "status": "publish",
    "content": "Iconic casino resort featuring 1,500 gaming machines, 56 table games, multiple restaurants including Hard Rock Cafe and Ruth's Chris, live entertainment, and a beachfront pool.",
    "excerpt": "",
    "post_date": "2026-03-10T12:00:00",
    "address": "777 Beach Blvd, Biloxi, MS 39530",
    "phone": "(228) 374-7625",
    "email": "",
    "website": "https://www.hardrockcasinobiloxi.com/",
    "latitude": "",
    "longitude": "",
    "featured": false,
    "categories": ["Accommodations"],
    "location": ["Biloxi"],
    "tags": [],
    "deal_title": "",
    "deal_description": "",
    "deal_expiry": ""
  },
  {
    "id": 33,
    "title": "IP Casino Resort Spa",
    "slug": "ip-casino-resort-spa",
    "status": "publish",
    "content": "AAA Four Diamond award-winning 32-story resort with 2,000 gaming machines, 78 game tables, 10 restaurants and bars, a full-service spa, and stunning water views.",
    "excerpt": "",
    "post_date": "2026-03-10T12:00:00",
    "address": "850 Bayview Ave, Biloxi, MS 39530",
    "phone": "(228) 436-3000",
    "email": "",
    "website": "https://ipbiloxi.boydgaming.com/",
    "latitude": "",
    "longitude": "",
    "featured": false,
    "categories": ["Accommodations"],
    "location": ["Biloxi"],
    "tags": [],
    "deal_title": "",
    "deal_description": "",
    "deal_expiry": ""
  },
  {
    "id": 34,
    "title": "Palace Casino Resort",
    "slug": "palace-casino-resort",
    "status": "publish",
    "content": "Highly rated waterfront casino resort with full-service spa, outdoor pool, gaming floor, multiple restaurants, and a free airport shuttle. Located on Biloxi's Back Bay.",
    "excerpt": "",
    "post_date": "2026-03-10T12:00:00",
    "address": "158 Howard Ave, Biloxi, MS 39530",
    "phone": "(228) 432-8888",
    "email": "",
    "website": "https://www.palacecasinoresort.com/",
    "latitude": "",
    "longitude": "",
    "featured": false,
    "categories": ["Accommodations"],
    "location": ["Biloxi"],
    "tags": [],
    "deal_title": "",
    "deal_description": "",
    "deal_expiry": ""
  },
  {
    "id": 35,
    "title": "Golden Nugget Biloxi",
    "slug": "golden-nugget-biloxi",
    "status": "publish",
    "content": "Casino, hotel, and marina featuring 49 gaming tables, 1,159 slot machines, a spa and salon, pool, and multiple dining options along the Gulf Coast.",
    "excerpt": "",
    "post_date": "2026-03-10T12:00:00",
    "address": "151 Beach Blvd, Biloxi, MS 39530",
    "phone": "(228) 435-5400",
    "email": "",
    "website": "https://www.goldennugget.com/biloxi/",
    "latitude": "",
    "longitude": "",
    "featured": false,
    "categories": ["Accommodations"],
    "location": ["Biloxi"],
    "tags": [],
    "deal_title": "",
    "deal_description": "",
    "deal_expiry": ""
  },
  {
    "id": 36,
    "title": "Harrah's Gulf Coast",
    "slug": "harrahs-gulf-coast",
    "status": "publish",
    "content": "Caesars Entertainment casino resort nestled on the beaches of Biloxi featuring gaming, dining, a pool, and Gulf Coast hospitality.",
    "excerpt": "",
    "post_date": "2026-03-10T12:00:00",
    "address": "280 Beach Blvd, Biloxi, MS 39530",
    "phone": "(228) 436-2946",
    "email": "",
    "website": "https://www.caesars.com/harrahs-gulf-coast",
    "latitude": "",
    "longitude": "",
    "featured": false,
    "categories": ["Accommodations"],
    "location": ["Biloxi"],
    "tags": [],
    "deal_title": "",
    "deal_description": "",
    "deal_expiry": ""
  },
  {
    "id": 37,
    "title": "Treasure Bay Casino & Hotel",
    "slug": "treasure-bay-casino-and-hotel",
    "status": "publish",
    "content": "Non-smoking casino hotel with 249 rooms and over 800 gaming options including 22 table games. Located on Beach Boulevard with Gulf views.",
    "excerpt": "",
    "post_date": "2026-03-10T12:00:00",
    "address": "1980 Beach Blvd, Biloxi, MS 39531",
    "phone": "(228) 385-6000",
    "email": "",
    "website": "https://www.treasurebay.com/",
    "latitude": "",
    "longitude": "",
    "featured": false,
    "categories": ["Accommodations"],
    "location": ["Biloxi"],
    "tags": [],
    "deal_title": "",
    "deal_description": "",
    "deal_expiry": ""
  },
  {
    "id": 38,
    "title": "Island View Casino Resort",
    "slug": "island-view-casino-resort",
    "status": "publish",
    "content": "Full-service casino resort on the beach in Gulfport featuring gaming, multiple restaurants, live entertainment, a hotel, and an event center.",
    "excerpt": "",
    "post_date": "2026-03-10T12:00:00",
    "address": "3300 W Beach Blvd, Gulfport, MS 39501",
    "phone": "(228) 314-2100",
    "email": "",
    "website": "https://www.islandviewcasino.com/",
    "latitude": "",
    "longitude": "",
    "featured": false,
    "categories": ["Accommodations"],
    "location": ["Gulfport"],
    "tags": [],
    "deal_title": "",
    "deal_description": "",
    "deal_expiry": ""
  },
  {
    "id": 39,
    "title": "Scarlet Pearl Casino Resort",
    "slug": "scarlet-pearl-casino-resort",
    "status": "publish",
    "content": "Modern casino resort in D'Iberville featuring gaming, outdoor pool, gym, multiple restaurants including Under the Oak Cafe and Scarlet's Steaks & Seafood, and free valet parking.",
    "excerpt": "",
    "post_date": "2026-03-10T12:00:00",
    "address": "9380 Central Ave, D'Iberville, MS 39540",
    "phone": "(228) 392-1889",
    "email": "",
    "website": "https://www.scarletpearlcasino.com/",
    "latitude": "",
    "longitude": "",
    "featured": false,
    "categories": ["Accommodations"],
    "location": ["D'Iberville"],
    "tags": [],
    "deal_title": "",
    "deal_description": "",
    "deal_expiry": ""
  },
  {
    "id": 40,
    "title": "Margaritaville Resort Biloxi",
    "slug": "margaritaville-resort-biloxi",
    "status": "publish",
    "content": "Tropical-themed resort near the beach featuring a vibrant pool area, on-site dining, tiki bar, and island-inspired amenities along Biloxi's casino row.",
    "excerpt": "",
    "post_date": "2026-03-10T12:00:00",
    "address": "195 Beach Blvd, Biloxi, MS 39530",
    "phone": "(228) 432-8550",
    "email": "",
    "website": "https://www.margaritavilleresortbiloxi.com/",
    "latitude": "",
    "longitude": "",
    "featured": false,
    "categories": ["Accommodations"],
    "location": ["Biloxi"],
    "tags": [],
    "deal_title": "",
    "deal_description": "",
    "deal_expiry": ""
  },
  {
    "id": 41,
    "title": "Memorial Hospital Gulfport",
    "slug": "memorial-hospital-gulfport",
    "status": "publish",
    "content": "Major regional hospital providing world-class emergency, surgical, cancer, cardiac, and neuroscience care to south Mississippi and the Gulf Coast.",
    "excerpt": "",
    "post_date": "2026-03-10T12:00:00",
    "address": "4500 13th St, Gulfport, MS 39501",
    "phone": "(228) 867-4000",
    "email": "",
    "website": "https://wearememorial.com/",
    "latitude": "",
    "longitude": "",
    "featured": false,
    "categories": ["Health & Medical"],
    "location": ["Gulfport"],
    "tags": [],
    "deal_title": "",
    "deal_description": "",
    "deal_expiry": ""
  },
  {
    "id": 42,
    "title": "Garden Park Medical Center",
    "slug": "garden-park-medical-center",
    "status": "publish",
    "content": "130-bed acute care hospital at the intersection of I-10 and Hwy 49 providing 24-hour emergency services, surgical care, and comprehensive inpatient and outpatient services.",
    "excerpt": "",
    "post_date": "2026-03-10T12:00:00",
    "address": "15200 Community Rd, Gulfport, MS 39503",
    "phone": "(228) 575-7000",
    "email": "",
    "website": "https://gardenparkmedical.com/",
    "latitude": "",
    "longitude": "",
    "featured": false,
    "categories": ["Health & Medical"],
    "location": ["Gulfport"],
    "tags": [],
    "deal_title": "",
    "deal_description": "",
    "deal_expiry": ""
  },
  {
    "id": 43,
    "title": "Merit Health Biloxi",
    "slug": "merit-health-biloxi",
    "status": "publish",
    "content": "Full-service hospital in Biloxi offering emergency care, surgical services, and a wide range of medical specialties for the Gulf Coast community.",
    "excerpt": "",
    "post_date": "2026-03-10T12:00:00",
    "address": "150 Reynoir St, Biloxi, MS 39530",
    "phone": "(228) 436-1104",
    "email": "",
    "website": "https://www.merithealthbiloxi.com/",
    "latitude": "",
    "longitude": "",
    "featured": false,
    "categories": ["Health & Medical"],
    "location": ["Biloxi"],
    "tags": [],
    "deal_title": "",
    "deal_description": "",
    "deal_expiry": ""
  },
  {
    "id": 44,
    "title": "Coastal Family Health Center",
    "slug": "coastal-family-health-center",
    "status": "publish",
    "content": "Fourth-largest community health center in Mississippi caring for over 36,000 patients annually. Offers primary care, preventive medicine, and accepts sliding-scale fees.",
    "excerpt": "",
    "post_date": "2026-03-10T12:00:00",
    "address": "715A Division St, Biloxi, MS 39530",
    "phone": "(228) 374-4991",
    "email": "",
    "website": "https://coastalfamilyhealth.org/",
    "latitude": "",
    "longitude": "",
    "featured": false,
    "categories": ["Health & Medical"],
    "location": ["Biloxi"],
    "tags": [],
    "deal_title": "",
    "deal_description": "",
    "deal_expiry": ""
  },
  {
    "id": 45,
    "title": "Biloxi VA Medical Center",
    "slug": "biloxi-va-medical-center",
    "status": "publish",
    "content": "Veterans Affairs medical center providing comprehensive health care to veterans including primary care, mental health, intensive care, and specialty services.",
    "excerpt": "",
    "post_date": "2026-03-10T12:00:00",
    "address": "400 Veterans Ave, Biloxi, MS 39531",
    "phone": "(228) 523-5000",
    "email": "",
    "website": "https://www.va.gov/gulf-coast-health-care/",
    "latitude": "",
    "longitude": "",
    "featured": false,
    "categories": ["Health & Medical"],
    "location": ["Biloxi"],
    "tags": [],
    "deal_title": "",
    "deal_description": "",
    "deal_expiry": ""
  },
  {
    "id": 46,
    "title": "Ochsner Health Center Gulfport",
    "slug": "ochsner-health-center-gulfport",
    "status": "publish",
    "content": "Multi-specialty health center offering primary care, specialty consultations, and diagnostic services with online patient portal access.",
    "excerpt": "",
    "post_date": "2026-03-10T12:00:00",
    "address": "15410 Community Rd, Gulfport, MS 39503",
    "phone": "(228) 575-3800",
    "email": "",
    "website": "https://www.ochsner.org/",
    "latitude": "",
    "longitude": "",
    "featured": false,
    "categories": ["Health & Medical"],
    "location": ["Gulfport"],
    "tags": [],
    "deal_title": "",
    "deal_description": "",
    "deal_expiry": ""
  },
  {
    "id": 47,
    "title": "Bethel Free Health Clinic",
    "slug": "bethel-free-health-clinic",
    "status": "publish",
    "content": "501(c)(3) nonprofit clinic founded after Hurricane Katrina to provide free medical care to uninsured Gulf Coast residents. Offers primary care and wellness services.",
    "excerpt": "",
    "post_date": "2026-03-10T12:00:00",
    "address": "1600 W Railroad St, Gulfport, MS 39501",
    "phone": "(228) 233-1850",
    "email": "",
    "website": "https://bethelfreeclinic.org/",
    "latitude": "",
    "longitude": "",
    "featured": false,
    "categories": ["Health & Medical"],
    "location": ["Gulfport"],
    "tags": [],
    "deal_title": "",
    "deal_description": "",
    "deal_expiry": ""
  },
  {
    "id": 48,
    "title": "Biloxi Internal Medicine Clinic",
    "slug": "biloxi-internal-medicine-clinic",
    "status": "publish",
    "content": "Internal medicine practice providing compassionate primary care for teens and adults with specialized services in adult medicine and chronic disease management.",
    "excerpt": "",
    "post_date": "2026-03-10T12:00:00",
    "address": "2280 Pass Rd, Biloxi, MS 39531",
    "phone": "(228) 396-5050",
    "email": "",
    "website": "https://www.biloxiinternal.com/",
    "latitude": "",
    "longitude": "",
    "featured": false,
    "categories": ["Health & Medical"],
    "location": ["Biloxi"],
    "tags": [],
    "deal_title": "",
    "deal_description": "",
    "deal_expiry": ""
  },
  {
    "id": 49,
    "title": "Seal's Tire & Auto Repair",
    "slug": "seals-tire-and-auto-repair",
    "status": "publish",
    "content": "Certified NAPA AutoCare Center with ASE-certified technicians and a 4.9-star rating. Offers a nationwide 24-month/24k-mile warranty on repairs for domestic and foreign vehicles.",
    "excerpt": "",
    "post_date": "2026-03-10T12:00:00",
    "address": "3200 25th Ave, Gulfport, MS 39501",
    "phone": "(228) 863-0068",
    "email": "",
    "website": "https://www.sealstires.com/",
    "latitude": "",
    "longitude": "",
    "featured": false,
    "categories": ["Auto Services"],
    "location": ["Gulfport"],
    "tags": [],
    "deal_title": "",
    "deal_description": "",
    "deal_expiry": ""
  },
  {
    "id": 50,
    "title": "Dependable Auto Repair",
    "slug": "dependable-auto-repair",
    "status": "publish",
    "content": "Full-service auto repair shop specializing in oil changes, brakes, engines, transmissions, and tires. Offers convenient after-hours pick-up and drop-off service.",
    "excerpt": "",
    "post_date": "2026-03-10T12:00:00",
    "address": "14187 Dedeaux Rd, Gulfport, MS 39503",
    "phone": "(228) 832-3600",
    "email": "",
    "website": "https://dependableautorepairms.com/",
    "latitude": "",
    "longitude": "",
    "featured": false,
    "categories": ["Auto Services"],
    "location": ["Gulfport"],
    "tags": [],
    "deal_title": "",
    "deal_description": "",
    "deal_expiry": ""
  },
  {
    "id": 51,
    "title": "Precision Tune Auto Care",
    "slug": "precision-tune-auto-care",
    "status": "publish",
    "content": "Full-service auto care center rated 4.6 stars offering oil changes, brake repairs, battery services, and scheduled maintenance for domestic and European vehicles.",
    "excerpt": "",
    "post_date": "2026-03-10T12:00:00",
    "address": "2510 25th Ave, Gulfport, MS 39501",
    "phone": "(228) 575-3484",
    "email": "",
    "website": "https://precisiontune.com/locations/gulfport-ms/",
    "latitude": "",
    "longitude": "",
    "featured": false,
    "categories": ["Auto Services"],
    "location": ["Gulfport"],
    "tags": [],
    "deal_title": "",
    "deal_description": "",
    "deal_expiry": ""
  },
  {
    "id": 52,
    "title": "Randall's Autohaus",
    "slug": "randalls-autohaus",
    "status": "publish",
    "content": "European vehicle specialist with ASE-certified technicians specializing in BMW, Mercedes-Benz, Audi, and Volkswagen repair and maintenance.",
    "excerpt": "",
    "post_date": "2026-03-10T12:00:00",
    "address": "11431 Lorraine Rd, Gulfport, MS 39503",
    "phone": "(228) 832-4377",
    "email": "",
    "website": "https://www.randallsauto.com/",
    "latitude": "",
    "longitude": "",
    "featured": false,
    "categories": ["Auto Services"],
    "location": ["Gulfport"],
    "tags": [],
    "deal_title": "",
    "deal_description": "",
    "deal_expiry": ""
  },
  {
    "id": 53,
    "title": "CJ's Automotive",
    "slug": "cjs-automotive",
    "status": "publish",
    "content": "NAPA-affiliated auto repair shop on Pass Road providing reliable automotive repair, maintenance, and diagnostic services to the Gulfport community.",
    "excerpt": "",
    "post_date": "2026-03-10T12:00:00",
    "address": "826 Pass Rd, Gulfport, MS 39501",
    "phone": "(228) 864-5411",
    "email": "",
    "website": "",
    "latitude": "",
    "longitude": "",
    "featured": false,
    "categories": ["Auto Services"],
    "location": ["Gulfport"],
    "tags": [],
    "deal_title": "",
    "deal_description": "",
    "deal_expiry": ""
  },
  {
    "id": 54,
    "title": "Randy Barras Salon",
    "slug": "randy-barras-salon",
    "status": "publish",
    "content": "Full-service salon and spa in historic downtown Biloxi offering classic cuts, specialty updos, facials, and massages. Over 40 years of experience, just a block from the Gulf.",
    "excerpt": "",
    "post_date": "2026-03-10T12:00:00",
    "address": "773 Howard Ave, Biloxi, MS 39530",
    "phone": "(228) 432-5959",
    "email": "",
    "website": "https://www.randybarras.com/",
    "latitude": "",
    "longitude": "",
    "featured": false,
    "categories": ["Beauty & Personal Care"],
    "location": ["Biloxi"],
    "tags": [],
    "deal_title": "",
    "deal_description": "",
    "deal_expiry": ""
  },
  {
    "id": 55,
    "title": "Val's Hair Gallery",
    "slug": "vals-hair-gallery",
    "status": "publish",
    "content": "Established hair salon pampering and beautifying the Biloxi community since 2004. Known for exceptional service and a welcoming atmosphere.",
    "excerpt": "",
    "post_date": "2026-03-10T12:00:00",
    "address": "1698 Pass Rd, Biloxi, MS 39531",
    "phone": "(228) 374-8247",
    "email": "",
    "website": "https://www.valshairgallery.com/",
    "latitude": "",
    "longitude": "",
    "featured": false,
    "categories": ["Beauty & Personal Care"],
    "location": ["Biloxi"],
    "tags": [],
    "deal_title": "",
    "deal_description": "",
    "deal_expiry": ""
  },
  {
    "id": 56,
    "title": "Trendsetters Barber Shop",
    "slug": "trendsetters-barber-shop",
    "status": "publish",
    "content": "Highly rated barbershop known as the best in Biloxi, offering precision cuts, fades, beard trims, and grooming services in a friendly environment.",
    "excerpt": "",
    "post_date": "2026-03-10T12:00:00",
    "address": "2200 Pass Rd, Biloxi, MS 39531",
    "phone": "(228) 388-2040",
    "email": "",
    "website": "",
    "latitude": "",
    "longitude": "",
    "featured": false,
    "categories": ["Beauty & Personal Care"],
    "location": ["Biloxi"],
    "tags": [],
    "deal_title": "",
    "deal_description": "",
    "deal_expiry": ""
  },
  {
    "id": 57,
    "title": "Lavish Salon",
    "slug": "lavish-salon-biloxi",
    "status": "publish",
    "content": "Modern salon on Rue Magnolia offering hair cuts, color, styling, and beauty treatments in a chic downtown Biloxi setting.",
    "excerpt": "",
    "post_date": "2026-03-10T12:00:00",
    "address": "132 Rue Magnolia, Biloxi, MS 39530",
    "phone": "(228) 263-1571",
    "email": "",
    "website": "",
    "latitude": "",
    "longitude": "",
    "featured": false,
    "categories": ["Beauty & Personal Care"],
    "location": ["Biloxi"],
    "tags": [],
    "deal_title": "",
    "deal_description": "",
    "deal_expiry": ""
  },
  {
    "id": 58,
    "title": "Ohr-O'Keefe Museum of Art",
    "slug": "ohr-okeefe-museum-of-art",
    "status": "publish",
    "content": "Frank Gehry-designed museum showcasing George Ohr pottery and Coastal Mississippi art. Features distinctive silver architecture and rotating exhibitions.",
    "excerpt": "",
    "post_date": "2026-03-10T12:00:00",
    "address": "386 Beach Blvd, Biloxi, MS 39530",
    "phone": "(228) 374-5547",
    "email": "",
    "website": "https://www.georgeohr.org/",
    "latitude": "",
    "longitude": "",
    "featured": false,
    "categories": ["Arts & Entertainment"],
    "location": ["Biloxi"],
    "tags": [],
    "deal_title": "",
    "deal_description": "",
    "deal_expiry": ""
  },
  {
    "id": 59,
    "title": "Maritime & Seafood Industry Museum",
    "slug": "maritime-and-seafood-industry-museum",
    "status": "publish",
    "content": "Museum preserving the maritime history and heritage of the Mississippi Gulf Coast since 1986 with exhibits, artifacts, and an extraordinary photograph collection.",
    "excerpt": "",
    "post_date": "2026-03-10T12:00:00",
    "address": "115 1st St, Biloxi, MS 39530",
    "phone": "(228) 435-6320",
    "email": "",
    "website": "https://www.maritimemuseum.org/",
    "latitude": "",
    "longitude": "",
    "featured": false,
    "categories": ["Arts & Entertainment"],
    "location": ["Biloxi"],
    "tags": [],
    "deal_title": "",
    "deal_description": "",
    "deal_expiry": ""
  },
  {
    "id": 60,
    "title": "Beauvoir - The Jefferson Davis Home",
    "slug": "beauvoir-jefferson-davis-home",
    "status": "publish",
    "content": "Historic 51-acre seaside estate of Jefferson Davis featuring a restored antebellum home, presidential library, soldier's cemetery, and nature trails.",
    "excerpt": "",
    "post_date": "2026-03-10T12:00:00",
    "address": "2244 Beach Blvd, Biloxi, MS 39531",
    "phone": "(228) 388-4400",
    "email": "",
    "website": "https://www.visitbeauvoir.org/",
    "latitude": "",
    "longitude": "",
    "featured": false,
    "categories": ["Arts & Entertainment"],
    "location": ["Biloxi"],
    "tags": [],
    "deal_title": "",
    "deal_description": "",
    "deal_expiry": ""
  },
  {
    "id": 61,
    "title": "Mississippi Aquarium",
    "slug": "mississippi-aquarium",
    "status": "publish",
    "content": "State-of-the-art aquarium spanning six acres with indoor and outdoor habitats featuring dolphins, otters, sharks, rays, and one of only a few 360-degree underwater tunnels in the country.",
    "excerpt": "",
    "post_date": "2026-03-10T12:00:00",
    "address": "2100 E Beach Blvd, Gulfport, MS 39501",
    "phone": "(228) 241-1300",
    "email": "",
    "website": "https://www.msaquarium.org/",
    "latitude": "",
    "longitude": "",
    "featured": false,
    "categories": ["Arts & Entertainment"],
    "location": ["Gulfport"],
    "tags": [],
    "deal_title": "",
    "deal_description": "",
    "deal_expiry": ""
  },
  {
    "id": 62,
    "title": "Lynn Meadows Discovery Center",
    "slug": "lynn-meadows-discovery-center",
    "status": "publish",
    "content": "Children's museum housed in a 1915 schoolhouse with 15,000 square feet of hands-on exhibits encouraging learning and creativity, located blocks from the beach.",
    "excerpt": "",
    "post_date": "2026-03-10T12:00:00",
    "address": "246 Dolan Ave, Gulfport, MS 39507",
    "phone": "(228) 897-6039",
    "email": "",
    "website": "https://www.lmdc.org/",
    "latitude": "",
    "longitude": "",
    "featured": false,
    "categories": ["Arts & Entertainment"],
    "location": ["Gulfport"],
    "tags": [],
    "deal_title": "",
    "deal_description": "",
    "deal_expiry": ""
  },
  {
    "id": 63,
    "title": "TrainTastic",
    "slug": "traintastic",
    "status": "publish",
    "content": "World's largest railroad museum featuring over 200 years of railroad history, the largest LEGO railroad display in Mississippi, multiple model train layouts, and riding trains.",
    "excerpt": "",
    "post_date": "2026-03-10T12:00:00",
    "address": "9146 Creative Dr, Gulfport, MS 39503",
    "phone": "(228) 224-5812",
    "email": "",
    "website": "https://www.traintastic.com/",
    "latitude": "",
    "longitude": "",
    "featured": false,
    "categories": ["Arts & Entertainment"],
    "location": ["Gulfport"],
    "tags": [],
    "deal_title": "",
    "deal_description": "",
    "deal_expiry": ""
  },
  {
    "id": 64,
    "title": "Gulf Islands Water Park",
    "slug": "gulf-islands-water-park",
    "status": "publish",
    "content": "Family water park in Gulfport featuring water slides, lazy rivers, wave pools, and splash areas for all ages. The Gulf Coast's premier summer attraction.",
    "excerpt": "",
    "post_date": "2026-03-10T12:00:00",
    "address": "17200 16th St, Gulfport, MS 39503",
    "phone": "(228) 328-1266",
    "email": "",
    "website": "https://www.gulfislandswaterpark.com/",
    "latitude": "",
    "longitude": "",
    "featured": false,
    "categories": ["Arts & Entertainment"],
    "location": ["Gulfport"],
    "tags": [],
    "deal_title": "",
    "deal_description": "",
    "deal_expiry": ""
  },
  {
    "id": 65,
    "title": "Biloxi Schooners",
    "slug": "biloxi-schooners",
    "status": "publish",
    "content": "Sail aboard 65-foot two-masted gaff-rigged Biloxi Oyster Schooners for scenic day sails and charters along the Mississippi Sound.",
    "excerpt": "",
    "post_date": "2026-03-10T12:00:00",
    "address": "386 Beach Blvd, Biloxi, MS 39530",
    "phone": "(228) 435-6320",
    "email": "",
    "website": "https://www.maritimemuseum.org/",
    "latitude": "",
    "longitude": "",
    "featured": false,
    "categories": ["Outdoors & Recreation"],
    "location": ["Biloxi"],
    "tags": [],
    "deal_title": "",
    "deal_description": "",
    "deal_expiry": ""
  },
  {
    "id": 66,
    "title": "Ship Island Excursions",
    "slug": "ship-island-excursions",
    "status": "publish",
    "content": "Scenic ferry service to the pristine Gulf Islands National Seashore barrier island for swimming, shelling, sunbathing, and exploring historic Fort Massachusetts.",
    "excerpt": "",
    "post_date": "2026-03-10T12:00:00",
    "address": "1040 23rd Ave, Gulfport, MS 39501",
    "phone": "(228) 864-1014",
    "email": "",
    "website": "https://www.msshipisland.com/",
    "latitude": "",
    "longitude": "",
    "featured": false,
    "categories": ["Outdoors & Recreation"],
    "location": ["Gulfport"],
    "tags": [],
    "deal_title": "",
    "deal_description": "",
    "deal_expiry": ""
  },
  {
    "id": 67,
    "title": "Banana's Mini Golf & Arcade",
    "slug": "bananas-mini-golf-and-arcade",
    "status": "publish",
    "content": "Family entertainment center featuring an exciting outdoor tropical 18-hole miniature golf course and indoor arcade games in Gulfport.",
    "excerpt": "",
    "post_date": "2026-03-10T12:00:00",
    "address": "12069 US-49, Gulfport, MS 39503",
    "phone": "(228) 328-1900",
    "email": "",
    "website": "",
    "latitude": "",
    "longitude": "",
    "featured": false,
    "categories": ["Outdoors & Recreation"],
    "location": ["Gulfport"],
    "tags": [],
    "deal_title": "",
    "deal_description": "",
    "deal_expiry": ""
  },
  {
    "id": 68,
    "title": "Ocean Adventures Marine Park",
    "slug": "ocean-adventures-marine-park",
    "status": "publish",
    "content": "Marine park offering up-close experiences and shows with dolphins, sea lions, sharks, rays, and tropical birds on the Mississippi Gulf Coast.",
    "excerpt": "",
    "post_date": "2026-03-10T12:00:00",
    "address": "10801 Dolphin Ln, Gulfport, MS 39503",
    "phone": "(228) 896-9182",
    "email": "",
    "website": "https://www.oceanadventures.net/",
    "latitude": "",
    "longitude": "",
    "featured": false,
    "categories": ["Outdoors & Recreation"],
    "location": ["Gulfport"],
    "tags": [],
    "deal_title": "",
    "deal_description": "",
    "deal_expiry": ""
  },
  {
    "id": 69,
    "title": "The Pet Clinic",
    "slug": "the-pet-clinic-biloxi",
    "status": "publish",
    "content": "Full-service veterinary clinic founded in 2001 providing dental care, laser therapy, medications, and boarding for dogs, cats, rabbits, pocket pets, and exotics.",
    "excerpt": "",
    "post_date": "2026-03-10T12:00:00",
    "address": "2430 Pass Rd, Biloxi, MS 39531",
    "phone": "(228) 392-0327",
    "email": "",
    "website": "https://www.petclinicgulfcoast.com/",
    "latitude": "",
    "longitude": "",
    "featured": false,
    "categories": ["Animal & Pet Services"],
    "location": ["Biloxi"],
    "tags": [],
    "deal_title": "",
    "deal_description": "",
    "deal_expiry": ""
  },
  {
    "id": 70,
    "title": "Handsboro Animal Hospital",
    "slug": "handsboro-animal-hospital",
    "status": "publish",
    "content": "Providing comprehensive veterinary services to companion pets on the Gulf Coast since the 1950s, promoting responsible pet ownership and preventative health care.",
    "excerpt": "",
    "post_date": "2026-03-10T12:00:00",
    "address": "341 Pass Rd, Gulfport, MS 39507",
    "phone": "(228) 896-3060",
    "email": "",
    "website": "https://www.handsboroanimal.com/",
    "latitude": "",
    "longitude": "",
    "featured": false,
    "categories": ["Animal & Pet Services"],
    "location": ["Gulfport"],
    "tags": [],
    "deal_title": "",
    "deal_description": "",
    "deal_expiry": ""
  },
  {
    "id": 71,
    "title": "Gulf Coast Veterinary Hospital",
    "slug": "gulf-coast-veterinary-hospital",
    "status": "publish",
    "content": "Established veterinary practice in Biloxi offering comprehensive medical, surgical, and preventive care for cats and dogs.",
    "excerpt": "",
    "post_date": "2026-03-10T12:00:00",
    "address": "1710 Pass Rd, Biloxi, MS 39531",
    "phone": "(228) 392-7800",
    "email": "",
    "website": "https://www.gulfcoastveterinaryhospital.com/",
    "latitude": "",
    "longitude": "",
    "featured": false,
    "categories": ["Animal & Pet Services"],
    "location": ["Biloxi"],
    "tags": [],
    "deal_title": "",
    "deal_description": "",
    "deal_expiry": ""
  },
  {
    "id": 72,
    "title": "Beach View Veterinary Hospital",
    "slug": "beach-view-veterinary-hospital",
    "status": "publish",
    "content": "Veteran veterinary practice serving Biloxi area pets for over four decades, specializing in vaccinations, preventative care, and flea and tick treatments.",
    "excerpt": "",
    "post_date": "2026-03-10T12:00:00",
    "address": "185 Porter Ave, Biloxi, MS 39530",
    "phone": "(228) 374-2727",
    "email": "",
    "website": "https://www.beachviewveterinaryhospital.com/",
    "latitude": "",
    "longitude": "",
    "featured": false,
    "categories": ["Animal & Pet Services"],
    "location": ["Biloxi"],
    "tags": [],
    "deal_title": "",
    "deal_description": "",
    "deal_expiry": ""
  },
  {
    "id": 73,
    "title": "Banfield Pet Hospital",
    "slug": "banfield-pet-hospital-gulfport",
    "status": "publish",
    "content": "Veterinary clinic providing quality health and wellness care for dogs, cats, and small animals with preventive care plans and walk-in availability.",
    "excerpt": "",
    "post_date": "2026-03-10T12:00:00",
    "address": "10540 Old Hwy 49, Gulfport, MS 39503",
    "phone": "(228) 896-2738",
    "email": "",
    "website": "https://www.banfield.com/",
    "latitude": "",
    "longitude": "",
    "featured": false,
    "categories": ["Animal & Pet Services"],
    "location": ["Gulfport"],
    "tags": [],
    "deal_title": "",
    "deal_description": "",
    "deal_expiry": ""
  },
  {
    "id": 74,
    "title": "Keesler Federal Credit Union",
    "slug": "keesler-federal-credit-union",
    "status": "publish",
    "content": "Award-winning credit union serving Mississippi, Louisiana, and Alabama. Named to Newsweek's America's Best Regional Banks and Credit Unions three consecutive years.",
    "excerpt": "",
    "post_date": "2026-03-10T12:00:00",
    "address": "2500 Pass Rd, Biloxi, MS 39531",
    "phone": "(228) 385-5500",
    "email": "",
    "website": "https://www.kfcu.org/",
    "latitude": "",
    "longitude": "",
    "featured": false,
    "categories": ["Financial Services"],
    "location": ["Biloxi"],
    "tags": [],
    "deal_title": "",
    "deal_description": "",
    "deal_expiry": ""
  },
  {
    "id": 75,
    "title": "Gulf Coast Community Federal Credit Union",
    "slug": "gulf-coast-community-fcu",
    "status": "publish",
    "content": "Local credit union delivering valued banking solutions including checking, savings, auto loans, mortgages, and personal loans to improve members' financial well-being.",
    "excerpt": "",
    "post_date": "2026-03-10T12:00:00",
    "address": "625 Division St, Biloxi, MS 39530",
    "phone": "(228) 374-2443",
    "email": "",
    "website": "https://www.gulfcoastcommunityfcu.com/",
    "latitude": "",
    "longitude": "",
    "featured": false,
    "categories": ["Financial Services"],
    "location": ["Biloxi"],
    "tags": [],
    "deal_title": "",
    "deal_description": "",
    "deal_expiry": ""
  },
  {
    "id": 76,
    "title": "Navigator Credit Union",
    "slug": "navigator-credit-union-gulfport",
    "status": "publish",
    "content": "Full-service credit union offering free checking, online and mobile banking, safe deposit boxes, notary services, and Co-Op Shared Branch access.",
    "excerpt": "",
    "post_date": "2026-03-10T12:00:00",
    "address": "2140 25th Ave, Gulfport, MS 39501",
    "phone": "(228) 475-8090",
    "email": "",
    "website": "https://navigatorcu.org/",
    "latitude": "",
    "longitude": "",
    "featured": false,
    "categories": ["Financial Services"],
    "location": ["Gulfport"],
    "tags": [],
    "deal_title": "",
    "deal_description": "",
    "deal_expiry": ""
  },
  {
    "id": 77,
    "title": "Regions Bank - Gulfport",
    "slug": "regions-bank-gulfport",
    "status": "publish",
    "content": "Full-service banking center offering personal and business banking, mortgages, wealth management, and financial planning services.",
    "excerpt": "",
    "post_date": "2026-03-10T12:00:00",
    "address": "2505 14th St, Gulfport, MS 39501",
    "phone": "(228) 868-5862",
    "email": "",
    "website": "https://www.regions.com/",
    "latitude": "",
    "longitude": "",
    "featured": false,
    "categories": ["Financial Services"],
    "location": ["Gulfport"],
    "tags": [],
    "deal_title": "",
    "deal_description": "",
    "deal_expiry": ""
  },
  {
    "id": 78,
    "title": "Hope Credit Union",
    "slug": "hope-credit-union-biloxi",
    "status": "publish",
    "content": "Community development credit union offering checking accounts, loans, credit cards, and financial services at their Mississippi Coast branch in Biloxi.",
    "excerpt": "",
    "post_date": "2026-03-10T12:00:00",
    "address": "946 Division St, Biloxi, MS 39530",
    "phone": "(228) 374-7394",
    "email": "",
    "website": "https://www.hopecu.org/",
    "latitude": "",
    "longitude": "",
    "featured": false,
    "categories": ["Financial Services"],
    "location": ["Biloxi"],
    "tags": [],
    "deal_title": "",
    "deal_description": "",
    "deal_expiry": ""
  },
  {
    "id": 79,
    "title": "ASAP Plumbing",
    "slug": "asap-plumbing-gulfport",
    "status": "publish",
    "content": "Residential and commercial plumbing company offering 24/7 emergency service, toilet installation, drain repair, and inspections throughout the Gulf Coast.",
    "excerpt": "",
    "post_date": "2026-03-10T12:00:00",
    "address": "14225 Dedeaux Rd, Gulfport, MS 39503",
    "phone": "(228) 202-6926",
    "email": "",
    "website": "https://plumbinggulfportms.com/",
    "latitude": "",
    "longitude": "",
    "featured": false,
    "categories": ["Home Services & Contractors"],
    "location": ["Gulfport"],
    "tags": [],
    "deal_title": "",
    "deal_description": "",
    "deal_expiry": ""
  },
  {
    "id": 80,
    "title": "Hansen Super Techs",
    "slug": "hansen-super-techs",
    "status": "publish",
    "content": "Full-service HVAC, plumbing, and electrical company with licensed technicians handling heating, cooling, electrical repairs, panel upgrades, and whole-home generator installation.",
    "excerpt": "",
    "post_date": "2026-03-10T12:00:00",
    "address": "12465 Hwy 67, Biloxi, MS 39532",
    "phone": "(228) 215-3141",
    "email": "",
    "website": "https://hansensupertechs.com/",
    "latitude": "",
    "longitude": "",
    "featured": false,
    "categories": ["Home Services & Contractors"],
    "location": ["Biloxi"],
    "tags": [],
    "deal_title": "",
    "deal_description": "",
    "deal_expiry": ""
  },
  {
    "id": 81,
    "title": "Lamey Electric",
    "slug": "lamey-electric",
    "status": "publish",
    "content": "Professional electrical contractor in Biloxi specializing in municipal, commercial, and residential electrical service and installations.",
    "excerpt": "",
    "post_date": "2026-03-10T12:00:00",
    "address": "10408 Lamey Bridge Rd, D'Iberville, MS 39540",
    "phone": "(228) 392-7070",
    "email": "",
    "website": "https://lameyelectric.com/",
    "latitude": "",
    "longitude": "",
    "featured": false,
    "categories": ["Home Services & Contractors"],
    "location": ["D'Iberville"],
    "tags": [],
    "deal_title": "",
    "deal_description": "",
    "deal_expiry": ""
  },
  {
    "id": 82,
    "title": "Teddy Bear Services",
    "slug": "teddy-bear-services",
    "status": "publish",
    "content": "Licensed and insured plumbing company delivering quality residential and commercial services for more than four decades across the Gulf Coast.",
    "excerpt": "",
    "post_date": "2026-03-10T12:00:00",
    "address": "2212 25th Ave, Gulfport, MS 39501",
    "phone": "(228) 896-0049",
    "email": "",
    "website": "https://www.teddybearservices.com/",
    "latitude": "",
    "longitude": "",
    "featured": false,
    "categories": ["Home Services & Contractors"],
    "location": ["Gulfport"],
    "tags": [],
    "deal_title": "",
    "deal_description": "",
    "deal_expiry": ""
  },
  {
    "id": 83,
    "title": "Gerard Construction",
    "slug": "gerard-construction",
    "status": "publish",
    "content": "Full-service home improvement contractor offering carpentry, decks, flooring, painting, siding, drywall, and fencing. Veteran and senior discounts available.",
    "excerpt": "",
    "post_date": "2026-03-10T12:00:00",
    "address": "Gulfport, MS 39501",
    "phone": "(228) 206-3725",
    "email": "",
    "website": "https://www.larrygerardinc.com/",
    "latitude": "",
    "longitude": "",
    "featured": false,
    "categories": ["Home Services & Contractors"],
    "location": ["Gulfport"],
    "tags": [],
    "deal_title": "",
    "deal_description": "",
    "deal_expiry": ""
  },
  {
    "id": 84,
    "title": "Gulfport Premium Outlets",
    "slug": "gulfport-premium-outlets",
    "status": "publish",
    "content": "Open-air outlet shopping center featuring more than 70 designer and brand-name stores including Coach, Nike, Michael Kors, and more at discounted prices.",
    "excerpt": "",
    "post_date": "2026-03-10T12:00:00",
    "address": "10000 Factory Shops Blvd, Gulfport, MS 39503",
    "phone": "(228) 867-6100",
    "email": "",
    "website": "https://www.premiumoutlets.com/outlet/gulfport",
    "latitude": "",
    "longitude": "",
    "featured": false,
    "categories": ["Shopping & Retail"],
    "location": ["Gulfport"],
    "tags": [],
    "deal_title": "",
    "deal_description": "",
    "deal_expiry": ""
  },
  {
    "id": 85,
    "title": "The Promenade D'Iberville",
    "slug": "the-promenade-diberville",
    "status": "publish",
    "content": "Open-air shopping and entertainment center featuring name-brand retail stores, restaurants, and entertainment options in the heart of D'Iberville.",
    "excerpt": "",
    "post_date": "2026-03-10T12:00:00",
    "address": "D'Iberville Blvd, D'Iberville, MS 39540",
    "phone": "(228) 396-4600",
    "email": "",
    "website": "",
    "latitude": "",
    "longitude": "",
    "featured": false,
    "categories": ["Shopping & Retail"],
    "location": ["D'Iberville"],
    "tags": [],
    "deal_title": "",
    "deal_description": "",
    "deal_expiry": ""
  },
  {
    "id": 86,
    "title": "Pass Christian Soap Company",
    "slug": "pass-christian-soap-company",
    "status": "publish",
    "content": "Locally owned boutique in downtown Pass Christian creating handcrafted artisan soaps, bath products, and gifts using natural ingredients.",
    "excerpt": "",
    "post_date": "2026-03-10T12:00:00",
    "address": "212 W Davis Ave, Pass Christian, MS 39571",
    "phone": "(228) 222-4029",
    "email": "",
    "website": "",
    "latitude": "",
    "longitude": "",
    "featured": false,
    "categories": ["Shopping & Retail"],
    "location": ["Pass Christian"],
    "tags": [],
    "deal_title": "",
    "deal_description": "",
    "deal_expiry": ""
  },
  {
    "id": 87,
    "title": "Martin Hardware",
    "slug": "martin-hardware-pass-christian",
    "status": "publish",
    "content": "Family-owned hardware store in downtown Pass Christian providing tools, building supplies, paint, and home improvement products to the local community.",
    "excerpt": "",
    "post_date": "2026-03-10T12:00:00",
    "address": "201 W Davis Ave, Pass Christian, MS 39571",
    "phone": "(228) 452-4311",
    "email": "",
    "website": "",
    "latitude": "",
    "longitude": "",
    "featured": false,
    "categories": ["Shopping & Retail"],
    "location": ["Pass Christian"],
    "tags": [],
    "deal_title": "",
    "deal_description": "",
    "deal_expiry": ""
  },
  {
    "id": 88,
    "title": "Sara Kate Clothing Boutique",
    "slug": "sara-kate-clothing-boutique",
    "status": "publish",
    "content": "Charming women's clothing boutique in downtown Pass Christian offering trendy and classic apparel, accessories, and gifts.",
    "excerpt": "",
    "post_date": "2026-03-10T12:00:00",
    "address": "120 W Davis Ave, Pass Christian, MS 39571",
    "phone": "(228) 452-0155",
    "email": "",
    "website": "",
    "latitude": "",
    "longitude": "",
    "featured": false,
    "categories": ["Shopping & Retail"],
    "location": ["Pass Christian"],
    "tags": [],
    "deal_title": "",
    "deal_description": "",
    "deal_expiry": ""
  },
  {
    "id": 89,
    "title": "First Baptist Church of Biloxi",
    "slug": "first-baptist-church-of-biloxi",
    "status": "publish",
    "content": "Historic Baptist church serving the Biloxi community with Sunday worship services, Bible study, youth programs, and community outreach ministries.",
    "excerpt": "",
    "post_date": "2026-03-10T12:00:00",
    "address": "924 Howard Ave, Biloxi, MS 39530",
    "phone": "(228) 374-6281",
    "email": "",
    "website": "",
    "latitude": "",
    "longitude": "",
    "featured": false,
    "categories": ["Churches & Religious"],
    "location": ["Biloxi"],
    "tags": [],
    "deal_title": "",
    "deal_description": "",
    "deal_expiry": ""
  },
  {
    "id": 90,
    "title": "Mosaic Church - Harrison County",
    "slug": "mosaic-church-harrison-county",
    "status": "publish",
    "content": "Non-denominational church with multiple Gulf Coast locations. The Harrison County campus offers contemporary worship, community groups, and family ministries.",
    "excerpt": "",
    "post_date": "2026-03-10T12:00:00",
    "address": "3320 Warrior Dr, D'Iberville, MS 39540",
    "phone": "(228) 818-9850",
    "email": "",
    "website": "https://www.mosaicgc.com/",
    "latitude": "",
    "longitude": "",
    "featured": false,
    "categories": ["Churches & Religious"],
    "location": ["D'Iberville"],
    "tags": [],
    "deal_title": "",
    "deal_description": "",
    "deal_expiry": ""
  },
  {
    "id": 91,
    "title": "Venture Church",
    "slug": "venture-church",
    "status": "publish",
    "content": "Community church in South Mississippi dedicated to leading people to know, love, and follow Jesus through worship services, small groups, and outreach.",
    "excerpt": "",
    "post_date": "2026-03-10T12:00:00",
    "address": "11252 Hwy 49, Gulfport, MS 39503",
    "phone": "(228) 832-9191",
    "email": "",
    "website": "https://www.venturechurch.org/",
    "latitude": "",
    "longitude": "",
    "featured": false,
    "categories": ["Churches & Religious"],
    "location": ["Gulfport"],
    "tags": [],
    "deal_title": "",
    "deal_description": "",
    "deal_expiry": ""
  },
  {
    "id": 92,
    "title": "First Baptist Church of Gulfport",
    "slug": "first-baptist-church-of-gulfport",
    "status": "publish",
    "content": "Established Baptist church in downtown Gulfport offering traditional and contemporary worship, children's programs, youth ministry, and missions.",
    "excerpt": "",
    "post_date": "2026-03-10T12:00:00",
    "address": "2400 15th St, Gulfport, MS 39501",
    "phone": "(228) 863-2671",
    "email": "",
    "website": "",
    "latitude": "",
    "longitude": "",
    "featured": false,
    "categories": ["Churches & Religious"],
    "location": ["Gulfport"],
    "tags": [],
    "deal_title": "",
    "deal_description": "",
    "deal_expiry": ""
  },
  {
    "id": 93,
    "title": "Church of the Nativity of the Blessed Virgin Mary",
    "slug": "church-of-the-nativity-bvm",
    "status": "publish",
    "content": "Historic Catholic parish in Biloxi with deep roots in the Gulf Coast's rich Catholic heritage. Offers Mass, sacraments, and community programs.",
    "excerpt": "",
    "post_date": "2026-03-10T12:00:00",
    "address": "871 Howard Ave, Biloxi, MS 39530",
    "phone": "(228) 374-3882",
    "email": "",
    "website": "",
    "latitude": "",
    "longitude": "",
    "featured": false,
    "categories": ["Churches & Religious"],
    "location": ["Biloxi"],
    "tags": [],
    "deal_title": "",
    "deal_description": "",
    "deal_expiry": ""
  },
  {
    "id": 94,
    "title": "University of Southern Mississippi - Gulf Park",
    "slug": "usm-gulf-park",
    "status": "publish",
    "content": "Regional campus of the University of Southern Mississippi located in Long Beach offering undergraduate and graduate degree programs with access to Gulf Coast research opportunities.",
    "excerpt": "",
    "post_date": "2026-03-10T12:00:00",
    "address": "730 E Beach Blvd, Long Beach, MS 39560",
    "phone": "(228) 865-4500",
    "email": "",
    "website": "https://www.usm.edu/gulf-park/",
    "latitude": "",
    "longitude": "",
    "featured": false,
    "categories": ["Education & Childcare"],
    "location": ["Long Beach"],
    "tags": [],
    "deal_title": "",
    "deal_description": "",
    "deal_expiry": ""
  },
  {
    "id": 95,
    "title": "Mississippi Gulf Coast Community College",
    "slug": "mgccc",
    "status": "publish",
    "content": "Community college with multiple Gulf Coast campuses offering associate degrees, technical programs, workforce training, and dual enrollment for high school students.",
    "excerpt": "",
    "post_date": "2026-03-10T12:00:00",
    "address": "2226 Switzer Rd, Gulfport, MS 39507",
    "phone": "(228) 897-3711",
    "email": "",
    "website": "https://www.mgccc.edu/",
    "latitude": "",
    "longitude": "",
    "featured": false,
    "categories": ["Education & Childcare"],
    "location": ["Gulfport"],
    "tags": [],
    "deal_title": "",
    "deal_description": "",
    "deal_expiry": ""
  },
  {
    "id": 96,
    "title": "Biloxi Public Schools",
    "slug": "biloxi-public-schools",
    "status": "publish",
    "content": "Public school district serving the Biloxi community with elementary, middle, and high schools committed to academic excellence and student achievement.",
    "excerpt": "",
    "post_date": "2026-03-10T12:00:00",
    "address": "160 St Peter St, Biloxi, MS 39530",
    "phone": "(228) 374-1810",
    "email": "",
    "website": "https://www.biloxischools.net/",
    "latitude": "",
    "longitude": "",
    "featured": false,
    "categories": ["Education & Childcare"],
    "location": ["Biloxi"],
    "tags": [],
    "deal_title": "",
    "deal_description": "",
    "deal_expiry": ""
  },
  {
    "id": 97,
    "title": "Gulfport School District",
    "slug": "gulfport-school-district",
    "status": "publish",
    "content": "Public school district serving Gulfport with elementary through high school education, special programs, and extracurricular activities.",
    "excerpt": "",
    "post_date": "2026-03-10T12:00:00",
    "address": "2001 Pass Rd, Gulfport, MS 39507",
    "phone": "(228) 865-4600",
    "email": "",
    "website": "https://www.gulfportschools.org/",
    "latitude": "",
    "longitude": "",
    "featured": false,
    "categories": ["Education & Childcare"],
    "location": ["Gulfport"],
    "tags": [],
    "deal_title": "",
    "deal_description": "",
    "deal_expiry": ""
  },
  {
    "id": 98,
    "title": "United Way of South Mississippi",
    "slug": "united-way-of-south-mississippi",
    "status": "publish",
    "content": "Nonprofit organization uniting resources to improve education, financial stability, and health outcomes across the Gulf Coast community.",
    "excerpt": "",
    "post_date": "2026-03-10T12:00:00",
    "address": "1600 Broad Ave, Gulfport, MS 39501",
    "phone": "(228) 896-1719",
    "email": "",
    "website": "https://www.unitedwaysms.org/",
    "latitude": "",
    "longitude": "",
    "featured": false,
    "categories": ["Community Services & Nonprofits"],
    "location": ["Gulfport"],
    "tags": [],
    "deal_title": "",
    "deal_description": "",
    "deal_expiry": ""
  },
  {
    "id": 99,
    "title": "Salvation Army Gulf Coast",
    "slug": "salvation-army-gulf-coast",
    "status": "publish",
    "content": "Community service organization providing disaster relief, food assistance, shelter, and family services to those in need across the Mississippi Gulf Coast.",
    "excerpt": "",
    "post_date": "2026-03-10T12:00:00",
    "address": "1520 Broad Ave, Gulfport, MS 39501",
    "phone": "(228) 863-7641",
    "email": "",
    "website": "https://www.salvationarmyusa.org/",
    "latitude": "",
    "longitude": "",
    "featured": false,
    "categories": ["Community Services & Nonprofits"],
    "location": ["Gulfport"],
    "tags": [],
    "deal_title": "",
    "deal_description": "",
    "deal_expiry": ""
  },
  {
    "id": 100,
    "title": "Boys & Girls Clubs of the Gulf Coast",
    "slug": "boys-and-girls-clubs-gulf-coast",
    "status": "publish",
    "content": "Youth development organization providing after-school programs, summer camps, mentoring, and recreational activities for young people on the Gulf Coast.",
    "excerpt": "",
    "post_date": "2026-03-10T12:00:00",
    "address": "232 Magnolia St, Biloxi, MS 39530",
    "phone": "(228) 435-0256",
    "email": "",
    "website": "",
    "latitude": "",
    "longitude": "",
    "featured": false,
    "categories": ["Community Services & Nonprofits"],
    "location": ["Biloxi"],
    "tags": [],
    "deal_title": "",
    "deal_description": "",
    "deal_expiry": ""
  },
  {
    "id": 101,
    "title": "Mississippi Gulf Coast Chamber of Commerce",
    "slug": "mississippi-gulf-coast-chamber-of-commerce",
    "status": "publish",
    "content": "Regional chamber of commerce supporting businesses across the Mississippi Gulf Coast through networking, advocacy, economic development, and member services.",
    "excerpt": "",
    "post_date": "2026-03-10T12:00:00",
    "address": "11975 Seaway Rd Bldg A, Gulfport, MS 39503",
    "phone": "(228) 604-0014",
    "email": "",
    "website": "https://mscoastchamber.com/",
    "latitude": "",
    "longitude": "",
    "featured": false,
    "categories": ["Community Services & Nonprofits"],
    "location": ["Gulfport"],
    "tags": [],
    "deal_title": "",
    "deal_description": "",
    "deal_expiry": ""
  },
  {
    "id": 102,
    "title": "Coldwell Banker Alfonso Realty",
    "slug": "coldwell-banker-alfonso-realty",
    "status": "publish",
    "content": "Full-service real estate agency helping buyers and sellers across the Mississippi Gulf Coast with residential and commercial properties.",
    "excerpt": "",
    "post_date": "2026-03-10T12:00:00",
    "address": "1625 E Pass Rd, Gulfport, MS 39507",
    "phone": "(228) 896-3773",
    "email": "",
    "website": "https://www.cbalfonsorealty.com/",
    "latitude": "",
    "longitude": "",
    "featured": false,
    "categories": ["Real Estate"],
    "location": ["Gulfport"],
    "tags": [],
    "deal_title": "",
    "deal_description": "",
    "deal_expiry": ""
  },
  {
    "id": 103,
    "title": "Keller Williams Realty - Gulf Coast",
    "slug": "keller-williams-realty-gulf-coast",
    "status": "publish",
    "content": "Leading real estate brokerage assisting with buying, selling, and investing in homes and properties across Harrison County and the Mississippi Gulf Coast.",
    "excerpt": "",
    "post_date": "2026-03-10T12:00:00",
    "address": "13001 US Hwy 49, Gulfport, MS 39503",
    "phone": "(228) 328-0808",
    "email": "",
    "website": "https://www.kw.com/",
    "latitude": "",
    "longitude": "",
    "featured": false,
    "categories": ["Real Estate"],
    "location": ["Gulfport"],
    "tags": [],
    "deal_title": "",
    "deal_description": "",
    "deal_expiry": ""
  },
  {
    "id": 104,
    "title": "RE/MAX Coast Delta Realty",
    "slug": "remax-coast-delta-realty",
    "status": "publish",
    "content": "Real estate agency specializing in Gulf Coast residential and waterfront properties with experienced agents serving Harrison County and beyond.",
    "excerpt": "",
    "post_date": "2026-03-10T12:00:00",
    "address": "2311 25th Ave, Gulfport, MS 39501",
    "phone": "(228) 896-7878",
    "email": "",
    "website": "https://www.remax.com/",
    "latitude": "",
    "longitude": "",
    "featured": false,
    "categories": ["Real Estate"],
    "location": ["Gulfport"],
    "tags": [],
    "deal_title": "",
    "deal_description": "",
    "deal_expiry": ""
  },
  {
    "id": 105,
    "title": "Coterie Long Beach",
    "slug": "coterie-long-beach",
    "status": "publish",
    "content": "New Orleans-inspired restaurant serving breakfast, lunch, and dinner daily with creative Southern dishes and cocktails in a cozy Long Beach setting.",
    "excerpt": "",
    "post_date": "2026-03-10T12:00:00",
    "address": "201 Jeff Davis Ave, Long Beach, MS 39560",
    "phone": "(228) 222-4033",
    "email": "",
    "website": "http://coterienola.com/",
    "latitude": "",
    "longitude": "",
    "featured": false,
    "categories": ["Restaurants & Dining"],
    "location": ["Long Beach"],
    "tags": [],
    "deal_title": "",
    "deal_description": "",
    "deal_expiry": ""
  },
  {
    "id": 106,
    "title": "Farmer Brown's Meat N Eat Fire Pit BBQ",
    "slug": "farmer-browns-meat-n-eat",
    "status": "publish",
    "content": "Barbecue restaurant in Saucier serving smoked meats, ribs, pulled pork, and classic Southern sides cooked over an open fire pit.",
    "excerpt": "",
    "post_date": "2026-03-10T12:00:00",
    "address": "23380 Hwy 49, Saucier, MS 39574",
    "phone": "(228) 832-2900",
    "email": "",
    "website": "",
    "latitude": "",
    "longitude": "",
    "featured": false,
    "categories": ["Restaurants & Dining"],
    "location": ["Saucier"],
    "tags": [],
    "deal_title": "",
    "deal_description": "",
    "deal_expiry": ""
  },
  {
    "id": 107,
    "title": "Old Cuevas Bistro & Bakery",
    "slug": "old-cuevas-bistro-and-bakery",
    "status": "publish",
    "content": "Charming bistro and bakery on Menge Avenue in Pass Christian serving fresh pastries, sandwiches, and creative brunch dishes.",
    "excerpt": "",
    "post_date": "2026-03-10T12:00:00",
    "address": "5331 Menge Ave, Pass Christian, MS 39571",
    "phone": "(228) 452-2253",
    "email": "",
    "website": "",
    "latitude": "",
    "longitude": "",
    "featured": false,
    "categories": ["Restaurants & Dining"],
    "location": ["Pass Christian"],
    "tags": [],
    "deal_title": "",
    "deal_description": "",
    "deal_expiry": ""
  },
  {
    "id": 108,
    "title": "Rock N Roll Sushi",
    "slug": "rock-n-roll-sushi-diberville",
    "status": "publish",
    "content": "American-style sushi restaurant with a rock and roll theme, offering creative sushi rolls, Asian fusion appetizers, and specialty drinks in D'Iberville.",
    "excerpt": "",
    "post_date": "2026-03-10T12:00:00",
    "address": "D'Iberville Blvd, D'Iberville, MS 39540",
    "phone": "(228) 432-4333",
    "email": "",
    "website": "",
    "latitude": "",
    "longitude": "",
    "featured": false,
    "categories": ["Restaurants & Dining"],
    "location": ["D'Iberville"],
    "tags": [],
    "deal_title": "",
    "deal_description": "",
    "deal_expiry": ""
  },
  {
    "id": 109,
    "title": "Southern AgCredit",
    "slug": "southern-agcredit-gulfport",
    "status": "publish",
    "content": "Full-service cooperative lender specializing in agricultural, rural land, and country home loans across the Mississippi Gulf Coast region.",
    "excerpt": "",
    "post_date": "2026-03-10T12:00:00",
    "address": "14206 S Hwy 49, Gulfport, MS 39503",
    "phone": "(228) 831-7009",
    "email": "",
    "website": "https://www.southernagcredit.com/",
    "latitude": "",
    "longitude": "",
    "featured": false,
    "categories": ["Financial Services"],
    "location": ["Gulfport"],
    "tags": [],
    "deal_title": "",
    "deal_description": "",
    "deal_expiry": ""
  },
  {
    "id": 110,
    "title": "A Royal Flush Plumbing",
    "slug": "a-royal-flush-plumbing",
    "status": "publish",
    "content": "Family-owned and operated plumbing contractor serving the community for over 20 years with residential and commercial plumbing, drain snaking, and backflow prevention.",
    "excerpt": "",
    "post_date": "2026-03-10T12:00:00",
    "address": "Gulfport, MS 39503",
    "phone": "(228) 832-9700",
    "email": "",
    "website": "",
    "latitude": "",
    "longitude": "",
    "featured": false,
    "categories": ["Home Services & Contractors"],
    "location": ["Gulfport"],
    "tags": [],
    "deal_title": "",
    "deal_description": "",
    "deal_expiry": ""
  },
  {
    "id": 111,
    "title": "Pass Wine & Spirits",
    "slug": "pass-wine-and-spirits",
    "status": "publish",
    "content": "Locally owned wine and spirits shop in downtown Pass Christian offering a curated selection of wines, craft spirits, and local favorites.",
    "excerpt": "",
    "post_date": "2026-03-10T12:00:00",
    "address": "106 W Davis Ave, Pass Christian, MS 39571",
    "phone": "(228) 452-9463",
    "email": "",
    "website": "",
    "latitude": "",
    "longitude": "",
    "featured": false,
    "categories": ["Shopping & Retail"],
    "location": ["Pass Christian"],
    "tags": [],
    "deal_title": "",
    "deal_description": "",
    "deal_expiry": ""
  },
  {
    "id": 112,
    "title": "Mullet Hop Trampoline Park",
    "slug": "mullet-hop-trampoline-park",
    "status": "publish",
    "content": "Indoor family entertainment center in D'Iberville featuring 12,000 square feet of trampolines, dodge ball, foam pits, and active fun for all ages.",
    "excerpt": "",
    "post_date": "2026-03-10T12:00:00",
    "address": "D'Iberville, MS 39540",
    "phone": "(228) 207-2900",
    "email": "",
    "website": "",
    "latitude": "",
    "longitude": "",
    "featured": false,
    "categories": ["Arts & Entertainment"],
    "location": ["D'Iberville"],
    "tags": [],
    "deal_title": "",
    "deal_description": "",
    "deal_expiry": ""
  },
  {
    "id": 113,
    "title": "Biloxi Lighthouse",
    "slug": "biloxi-lighthouse",
    "status": "publish",
    "content": "Iconic cast-iron lighthouse uniquely situated in the median of Highway 90. One of the few lighthouses open for public climbing with panoramic Gulf Coast views.",
    "excerpt": "",
    "post_date": "2026-03-10T12:00:00",
    "address": "1050 Beach Blvd, Biloxi, MS 39530",
    "phone": "(228) 374-3105",
    "email": "",
    "website": "",
    "latitude": "",
    "longitude": "",
    "featured": false,
    "categories": ["Arts & Entertainment"],
    "location": ["Biloxi"],
    "tags": [],
    "deal_title": "",
    "deal_description": "",
    "deal_expiry": ""
  },
  {
    "id": 114,
    "title": "C.Q. Skin & Wellness",
    "slug": "cq-skin-and-wellness",
    "status": "publish",
    "content": "Day spa in Biloxi dedicated to holistic well-being through revitalizing skin treatments, facials, and wellness services in a relaxing environment.",
    "excerpt": "",
    "post_date": "2026-03-10T12:00:00",
    "address": "Biloxi, MS 39530",
    "phone": "(228) 207-2550",
    "email": "",
    "website": "",
    "latitude": "",
    "longitude": "",
    "featured": false,
    "categories": ["Beauty & Personal Care"],
    "location": ["Biloxi"],
    "tags": [],
    "deal_title": "",
    "deal_description": "",
    "deal_expiry": ""
  },
  {
    "id": 115,
    "title": "Saucier Church of God",
    "slug": "saucier-church-of-god",
    "status": "publish",
    "content": "Community church in Saucier offering worship services, Bible study, and fellowship for families in the northern Harrison County area.",
    "excerpt": "",
    "post_date": "2026-03-10T12:00:00",
    "address": "23200 Hwy 49, Saucier, MS 39574",
    "phone": "(228) 832-3744",
    "email": "",
    "website": "",
    "latitude": "",
    "longitude": "",
    "featured": false,
    "categories": ["Churches & Religious"],
    "location": ["Saucier"],
    "tags": [],
    "deal_title": "",
    "deal_description": "",
    "deal_expiry": ""
  },
  {
    "id": 116,
    "title": "Edgewater Mall",
    "slug": "edgewater-mall",
    "status": "publish",
    "content": "Regional shopping mall in Biloxi featuring major retailers, department stores, specialty shops, a food court, and family entertainment.",
    "excerpt": "",
    "post_date": "2026-03-10T12:00:00",
    "address": "2600 Beach Blvd, Biloxi, MS 39531",
    "phone": "(228) 388-3424",
    "email": "",
    "website": "",
    "latitude": "",
    "longitude": "",
    "featured": false,
    "categories": ["Shopping & Retail"],
    "location": ["Biloxi"],
    "tags": [],
    "deal_title": "",
    "deal_description": "",
    "deal_expiry": ""
  },
  {
    "id": 117,
    "title": "Coast Professional Services",
    "slug": "coast-professional-services",
    "status": "publish",
    "content": "Professional accounting and business advisory firm providing tax preparation, bookkeeping, payroll, and consulting services to Gulf Coast businesses and individuals.",
    "excerpt": "",
    "post_date": "2026-03-10T12:00:00",
    "address": "2511 14th St, Gulfport, MS 39501",
    "phone": "(228) 863-4244",
    "email": "",
    "website": "",
    "latitude": "",
    "longitude": "",
    "featured": false,
    "categories": ["Professional Services"],
    "location": ["Gulfport"],
    "tags": [],
    "deal_title": "",
    "deal_description": "",
    "deal_expiry": ""
  },
  {
    "id": 118,
    "title": "Gulf Coast Legal Aid",
    "slug": "gulf-coast-legal-aid",
    "status": "publish",
    "content": "Nonprofit legal services organization providing free civil legal assistance to low-income individuals and families across the Mississippi Gulf Coast.",
    "excerpt": "",
    "post_date": "2026-03-10T12:00:00",
    "address": "Gulfport, MS 39501",
    "phone": "(228) 864-0558",
    "email": "",
    "website": "",
    "latitude": "",
    "longitude": "",
    "featured": false,
    "categories": ["Professional Services"],
    "location": ["Gulfport"],
    "tags": [],
    "deal_title": "",
    "deal_description": "",
    "deal_expiry": ""
  }
]
